lgtv_rs232/__init__.py
lgtv_rs232/lgtv.py
lgtv_rs232_zcline91-0.0.6.dist-info/LICENSE
lgtv_rs232_zcline91-0.0.6.dist-info/METADATA
lgtv_rs232_zcline91-0.0.6.dist-info/WHEEL
lgtv_rs232_zcline91-0.0.6.dist-info/top_level.txt
lgtv_rs232_zcline91-0.0.6.dist-info/RECORD
