Metadata-Version: 2.1
Name: lgtv-rs232-zcline91
Version: 0.0.6
Summary: A small package for controlling my LG TV through its serial port
Author-email: Zachary Cline <zachcline@gmail.com>
Project-URL: Homepage, https://github.com/zcline91/lgtv-rs232-zcline91
Project-URL: Repository, https://github.com/zcline91/lgtv-rs232-zcline91.git
Project-URL: Issues, https://github.com/zcline91/lgtv-rs232-zcline91/issues
Classifier: Programming Language :: Python :: 3
Classifier: License :: OSI Approved :: GNU General Public License v3 (GPLv3)
Classifier: Operating System :: Unix
Requires-Python: >=3.8
License-File: LICENSE
Requires-Dist: pyserial
